setuptools_trial/__init__.py
setuptools_trial/_version.py
setuptools_trial/setuptools_trial.py
setuptools_trial-0.6.0.data/data/share/doc/python-setuptools_trial/COPYING.SPL.txt
setuptools_trial-0.6.0.data/data/share/doc/python-setuptools_trial/README.rst
setuptools_trial-0.6.0.dist-info/DESCRIPTION.rst
setuptools_trial-0.6.0.dist-info/METADATA
setuptools_trial-0.6.0.dist-info/RECORD
setuptools_trial-0.6.0.dist-info/WHEEL
setuptools_trial-0.6.0.dist-info/entry_points.txt
setuptools_trial-0.6.0.dist-info/metadata.json
setuptools_trial-0.6.0.dist-info/top_level.txt
