Metadata-Version: 2.0
Name: setuptools-trial
Version: 0.6.0
Summary: Setuptools plugin that makes unit tests execute with trial instead of pyunit.
Home-page: https://github.com/rutsky/setuptools-trial
Author: Vladimir Rutsky
Author-email: vladimir@rutsky.org
License: BSD
Keywords: distutils setuptools trial setuptools_plugin
Platform: UNKNOWN
Classifier: Development Status :: 4 - Beta
Classifier: License :: OSI Approved :: BSD License
Classifier: License :: DFSG approved
Classifier: Intended Audience :: Developers
Classifier: Operating System :: OS Independent
Classifier: Natural Language :: English
Classifier: Programming Language :: Python
Classifier: Programming Language :: Python :: 2
Classifier: Programming Language :: Python :: 2.7
Classifier: Programming Language :: Python :: 3
Classifier: Topic :: Utilities
Classifier: Topic :: Software Development :: Libraries
Classifier: Framework :: Setuptools Plugin
Requires-Dist: Twisted (>=2.4.0)
Requires-Dist: pathlib2; python_version == '2.7'
